AUTHORS
CHANGES
MANIFEST.in
README
setup.cfg
setup.py
pybovespa/__init__.py
pybovespa/bovespa.py
pybovespa/exceptions.py
pybovespa/stock.py
pybovespa.egg-info/PKG-INFO
pybovespa.egg-info/SOURCES.txt
pybovespa.egg-info/dependency_links.txt
pybovespa.egg-info/top_level.txt