Metadata-Version: 1.1
Name: pybovespa
Version: 0.1.1
Summary: pybovespa is a basic library to get Bovespa stock values.
Home-page: http://gitorious.org/unix-stuff/pybovespa
Author: Beraldo Leal
Author-email: beraldo@beraloleal.com
License: MIT
Platform: Posix; MacOS X;
Classifier: Development Status :: 2 - Pre-Alpha
Classifier: Intended Audience :: Developers
Classifier: License :: OSI Approved :: MIT License
Classifier: Operating System :: POSIX
Classifier: Topic :: Software Development :: Libraries :: Python Modules
Classifier: Topic :: Internet
Classifier: Programming Language :: Python :: 3.2
